setup.py
caps_ms_1.egg-info/PKG-INFO
caps_ms_1.egg-info/SOURCES.txt
caps_ms_1.egg-info/dependency_links.txt
caps_ms_1.egg-info/requires.txt
caps_ms_1.egg-info/top_level.txt
modellingService/Constants.py
modellingService/Estimators.py
modellingService/Train.py
modellingService/Utils.py
modellingService/__init__.py