Metadata-Version: 1.0
Name: caps-ms-1
Version: 0.1
Summary: A pyspark package for modelling-service algorithms
Home-page: UNKNOWN
Author: CAPS-AN-EN
Author-email: caps-an-en@mediaiqdigital.com
License: UNKNOWN
Platform: UNKNOWN
